healthy/__init__.py
healthy/apps.py
healthy/backends.py
healthy/compat.py
healthy/handler.py
healthy/responses.py
healthy/urls.py
healthy/views.py
django_healthy-0.0.1a5.dist-info/METADATA
django_healthy-0.0.1a5.dist-info/WHEEL
django_healthy-0.0.1a5.dist-info/licenses/LICENSE.txt
django_healthy-0.0.1a5.dist-info/RECORD
