Metadata-Version: 2.3
Name: django-healthy
Version: 0.0.1a5
Summary: Simple health checking for django applications
Project-URL: Documentation, https://github.com/olist/django-healthy#readme
Project-URL: Issues, https://github.com/olist/django-healthy/issues
Project-URL: Source, https://github.com/olist/django-healthy
Author-email: Christian Hartung <christian.hartung@olist.com>
License-Expression: MIT
License-File: LICENSE.txt
Keywords: django
Classifier: Development Status :: 4 - Beta
Classifier: Framework :: Django :: 4.2
Classifier: Framework :: Django :: 5.0
Classifier: Programming Language :: Python
Classifier: Programming Language :: Python :: 3.8
Classifier: Programming Language :: Python :: 3.9
Classifier: Programming Language :: Python :: 3.10
Classifier: Programming Language :: Python :: 3.11
Classifier: Programming Language :: Python :: 3.12
Classifier: Programming Language :: Python :: Implementation :: CPython
Classifier: Programming Language :: Python :: Implementation :: PyPy
Requires-Python: >=3.8
Requires-Dist: asgiref
Requires-Dist: django>=4.2
Requires-Dist: typing-extensions; python_version < '3.12'
